dbt/adapters/cratedb/__init__.py
dbt/adapters/cratedb/__version__.py
dbt/adapters/cratedb/column.py
dbt/adapters/cratedb/connections.py
dbt/adapters/cratedb/impl.py
dbt/adapters/cratedb/relation.py
dbt/adapters/cratedb/util.py
dbt/adapters/cratedb/record/__init__.py
dbt/adapters/cratedb/record/handle.py
dbt/adapters/cratedb/relation_configs/__init__.py
dbt/adapters/cratedb/relation_configs/constants.py
dbt/adapters/cratedb/relation_configs/index.py
dbt/adapters/cratedb/relation_configs/materialized_view.py
dbt/include/cratedb/__init__.py
dbt/include/cratedb/dbt_project.yml
dbt/include/cratedb/profile_template.yml
dbt/include/cratedb/sample_profiles.yml
dbt/include/cratedb/macros/adapters.sql
dbt/include/cratedb/macros/catalog.sql
dbt/include/cratedb/macros/relations.sql
dbt/include/cratedb/macros/materializations/incremental.sql
dbt/include/cratedb/macros/materializations/seed.sql
dbt_cratedb2-0.1.1.dist-info/METADATA
dbt_cratedb2-0.1.1.dist-info/WHEEL
dbt_cratedb2-0.1.1.dist-info/licenses/LICENSE
dbt_cratedb2-0.1.1.dist-info/RECORD
