Metadata-Version: 2.3
Name: dbt-cratedb2
Version: 0.1.1
Summary: dbt adapter for CrateDB 5.5 and higher
Project-URL: Changelog, https://github.com/crate/dbt-cratedb2/blob/main/CHANGELOG.md
Project-URL: Documentation, https://cratedb.com/docs/guide/integrate/dbt/
Project-URL: Downloads, https://pypi.org/project/dbt-cratedb2/#files
Project-URL: Homepage, https://github.com/crate/dbt-cratedb2
Project-URL: Issues, https://github.com/crate/dbt-cratedb2/issues
Project-URL: Release Notes, https://github.com/crate/dbt-cratedb2/releases
Project-URL: Repository, https://github.com/crate/dbt-cratedb2
Project-URL: Source Code, https://github.com/crate/dbt-cratedb2
Author-email: "Crate.io" <office@crate.io>
Maintainer-email: "Crate.io" <office@crate.io>
Keywords: adapter,adapters,cratedb,database,dbt,dbt-adapter,dbt-core,elt,postgresql
Classifier: Development Status :: 4 - Beta
Classifier: License :: OSI Approved :: Apache Software License
Classifier: Operating System :: MacOS :: MacOS X
Classifier: Operating System :: Microsoft :: Windows
Classifier: Operating System :: OS Independent
Classifier: Operating System :: POSIX :: Linux
Classifier: Programming Language :: Python :: 3.9
Classifier: Programming Language :: Python :: 3.10
Classifier: Programming Language :: Python :: 3.11
Classifier: Programming Language :: Python :: 3.12
Classifier: Programming Language :: Python :: 3.13
Requires-Python: >=3.9.0
Requires-Dist: dbt-postgres<1.10,>=1.9.0
Requires-Dist: sql-metadata<3
Requires-Dist: sqlparse<0.6
